MANIFEST.in
README.md
setup.py
PyiAccess.egg-info/PKG-INFO
PyiAccess.egg-info/SOURCES.txt
PyiAccess.egg-info/dependency_links.txt
PyiAccess.egg-info/requires.txt
PyiAccess.egg-info/top_level.txt
pyiaccess/__init__.py
pyiaccess/db.py
pyiaccess/engine.py
pyiaccess/settings.py
pyiaccess/transfer.py
pyiaccess/helpers/__init__.py
pyiaccess/helpers/common.py