Metadata-Version: 2.1
Name: PyiAccess
Version: 0.2
Summary: It is a library that connects to IBM Power Systems (IBM i), with pyodbc and SSH connection.
Home-page: https://github.com/thomgonzalez/pyiaccess
Author: Tomás Santiago González
Author-email: thom.sgonzalez@gmail.com
License: UNKNOWN
Project-URL: Homepage, https://github.com/thomgonzalez/pyiaccess
Keywords: IBM i Access,iSeries,systems i,AS/400
Platform: UNKNOWN
Classifier: Programming Language :: Python
Classifier: Programming Language :: Python :: 3
Classifier: License :: OSI Approved :: MIT License
Classifier: Topic :: System :: Operating System Kernels :: Linux
Requires-Python: >=3.4
